win32_bridge/__init__.py
win32_bridge/capture.py
win32_bridge-0.0.0.0.dist-info/LICENSE
win32_bridge-0.0.0.0.dist-info/METADATA
win32_bridge-0.0.0.0.dist-info/WHEEL
win32_bridge-0.0.0.0.dist-info/top_level.txt
win32_bridge-0.0.0.0.dist-info/RECORD
